odoo/addons/wms_demo/__init__.py
odoo/addons/wms_demo/__manifest__.py
odoo/addons/wms_demo/demo/picking_type_demo.xml
odoo/addons/wms_demo/demo/picking_type_sequence_demo.xml
odoo/addons/wms_demo/demo/product_packaging_demo.xml
odoo/addons/wms_demo/demo/product_product_demo.xml
odoo/addons/wms_demo/demo/product_storage_tag_demo.xml
odoo/addons/wms_demo/demo/stock_location_bin_demo.xml
odoo/addons/wms_demo/demo/stock_location_demo.xml
odoo/addons/wms_demo/demo/stock_location_route_demo.xml
odoo/addons/wms_demo/demo/stock_putaway_rule_demo.xml
odoo/addons/wms_demo/demo/stock_reserve_rule_demo.xml
odoo/addons/wms_demo/demo/stock_rule_demo.xml
odoo/addons/wms_demo/demo/stock_warehouse_demo.xml
odoo/addons/wms_demo/i18n/it.po
odoo/addons/wms_demo/i18n/wms_demo.pot
odoo/addons/wms_demo/static/description/icon.png
odoo12_addon_wms_demo-12.0.1.0.0.99.dev4.dist-info/METADATA
odoo12_addon_wms_demo-12.0.1.0.0.99.dev4.dist-info/WHEEL
odoo12_addon_wms_demo-12.0.1.0.0.99.dev4.dist-info/top_level.txt
odoo12_addon_wms_demo-12.0.1.0.0.99.dev4.dist-info/RECORD
