Metadata-Version: 2.1
Name: odoo12-addon-wms-demo
Version: 12.0.1.0.0.99.dev4
Summary: Warehouse Management System
Home-page: UNKNOWN
Author: Camptocamp,Odoo Community Association (OCA)
Author-email: support@odoo-community.org
License: AGPL-3
Platform: UNKNOWN
Classifier: Programming Language :: Python
Classifier: Framework :: Odoo
Classifier: Framework :: Odoo :: 12.0
Classifier: License :: OSI Approved :: GNU Affero General Public License v3
Classifier: Development Status :: 3 - Alpha
Requires-Python: >=3.5
Requires-Dist: odoo12-addon-stock-move-location-dest-constraint-empty
Requires-Dist: odoo12-addon-stock-move-location-dest-constraint-tag
Requires-Dist: odoo12-addon-stock-picking-completion-info
Requires-Dist: odoo12-addon-stock-picking-type-routing-operation
Requires-Dist: odoo12-addon-stock-putaway-abc
Requires-Dist: odoo12-addon-stock-putaway-abc-move-location-dest-constraint
Requires-Dist: odoo12-addon-stock-putaway-recursive
Requires-Dist: odoo12-addon-stock-putaway-rule
Requires-Dist: odoo12-addon-stock-reserve-rule
Requires-Dist: odoo12-addon-stock-vertical-lift
Requires-Dist: odoo12-addon-wms
Requires-Dist: odoo <12.1dev,>=12.0a
